leaky_diode/__init__.py
leaky_diode/buffer.py
leaky_diode/client.py
leaky_diode/logger.py
leaky_diode/message.py
leaky_diode/server.py
leaky_diode-0.1.1.data/scripts/leaky_client
leaky_diode-0.1.1.data/scripts/leaky_server
leaky_diode-0.1.1.dist-info/LICENSE
leaky_diode-0.1.1.dist-info/METADATA
leaky_diode-0.1.1.dist-info/WHEEL
leaky_diode-0.1.1.dist-info/top_level.txt
leaky_diode-0.1.1.dist-info/zip-safe
leaky_diode-0.1.1.dist-info/RECORD
