Metadata-Version: 2.1
Name: leaky-diode
Version: 0.1.1
Summary: Leaky Diode is a data exfiltration test tool for data diodes,
Home-page: https://github.com/secnot/leaky_diode
Author: SecNot
Author-email: secnot@secnot.com
License: AGPLv3
Keywords: data diode,diode,cybersecurity,security,hack,hacking,data,leak,exfiltration,data exfiltration,flow modulation,close delay,attack,pentesting,penetration testing
Platform: UNKNOWN
Requires-Dist: pathlib
